{
  "orders": [
    {
      "id": 26782,
      "hotel_name": "MEALFUL WRAPS - Meals In A Wrap",
      "name": "Aakash",
      "email": "aakash@gmail.com",
      "cost": 388,
      "address": "Hno12",
      "menuItem": "46,47",
      "phone": "7576576"
    },
    {
      "id": 62193,
      "hotel_name": "Pandit Ji Paratha Hut",
      "name": "Bhumika",
      "email": "bhumika@gmail.com",
      "cost": 255,
      "address": "Hno12",
      "menuItem": "8,10,6",
      "phone": "6765465"
    },
    {
      "id": 13338,
      "hotel_name": "Cafe Wink",
      "name": "Aakash",
      "email": "aakash@gmail.com",
      "cost": 945,
      "address": "Hno12",
      "menuItem": "58,56,60",
      "phone": "6566587576"
    },
    {
      "id": 7527,
      "hotel_name": "The Appetite Momos",
      "name": "Bhumika",
      "email": "bhumika@gmail.com",
      "cost": 195,
      "address": "Hno12",
      "menuItem": "16,18",
      "phone": "76767436"
    },
    {
      "id": 39080,
      "hotel_name": "Domino's Pizza",
      "name": "Amit",
      "email": "amit@gmail.com",
      "cost": 577,
      "address": "Hno12",
      "menuItem": "1,2,3",
      "phone": "7678678"
    }
  ]
}